[
  {
    "id": "9",
    "title": "Aleph-0 [Ω]",
    "artist": "LeaF Movie:Optie / obj:1008",
    "level": "0",
    "md5": "2e2ec86581e880d8570d2f3b10c03fda",
    "sha256": "",
    "status": "accepted",
    "datetime": "",
    "proposer": "",
    "comment": "POTY2020"
  },
  {
    "id": "10",
    "title": "Aurora [Shine]",
    "artist": "Lime obj:Blocko",
    "level": "0",
    "md5": "5580e8407abef96a303cba82a1eb605c",
    "sha256": "",
    "status": "accepted",
    "datetime": "",
    "proposer": "",
    "comment": "POTY2019"
  },
  {
    "id": "11",
    "title": "HEXPERUS [NEXTAGE]",
    "artist": "qfeileadh&のあ mov:Kengo Nakao",
    "level": "0",
    "md5": "72b1ce4b2051bd2a396dfa11a2d785ee",
    "sha256": "",
    "status": "accepted",
    "datetime": "",
    "proposer": "",
    "comment": "POTY2021"
  },
  {
    "id": "12",
    "title": "Melotte 333 (EX7)",
    "artist": "sun3 / BGA:Johnny / nbunnyuwu_fix",
    "level": "0",
    "md5": "b8de66e52d4f4377ef8aab1d345627b3",
    "sha256": "",
    "status": "accepted",
    "datetime": "",
    "proposer": "",
    "comment": "POTY2022"
  },
  {
    "id": "13",
    "title": "TRI-TECH -Xe-",
    "artist": "ixi's Movie : TAKRIDER / obj:LindBlum",
    "level": "0",
    "md5": "4f050ea8f59ecb5b567d8d75c41fa799",
    "sha256": "",
    "status": "accepted",
    "datetime": "",
    "proposer": "",
    "comment": "POTY2022"
  },
  {
    "id": "14",
    "title": "アトロポスと最果の探求者 -Despair & Hope-",
    "artist": "しーけー obj:七海千秋",
    "level": "0",
    "md5": "7efd0cb03da8a2e1a4daf76dbcf5f142",
    "sha256": "",
    "status": "accepted",
    "datetime": "",
    "proposer": "",
    "comment": "POTY2019"
  },
  {
    "id": "15",
    "title": "タイヨウパラダイス(Lemon beads J-core bootleg) [R-18]",
    "artist": "nao/雪仁/水城新人 remixed by Lemon beads obj.hex",
    "level": "0",
    "md5": "98ce9d2537a1fe9b767fd495e1d7b339",
    "sha256": "",
    "status": "accepted",
    "datetime": "",
    "proposer": "",
    "comment": "POTY2019"
  },
  {
    "id": "16",
    "title": "ぽっぷる！ [delay party]",
    "artist": "Seichi Yumeno / obj. laner",
    "level": "0",
    "md5": "54122c5fe4306ef765cff0433b5a7176",
    "sha256": "",
    "status": "accepted",
    "datetime": "",
    "proposer": "",
    "comment": "POTY2021"
  },
  {
    "id": "17",
    "title": "花たちに希望を -To the Future-",
    "artist": "Sound piercer feat.DAZBEE NeLiME / CHERISH / fxxh / Feyrlin / selene.",
    "level": "0",
    "md5": "99e5d4a4d83d6fb16a830c57361da49b",
    "sha256": "",
    "status": "accepted",
    "datetime": "",
    "proposer": "",
    "comment": "POTY2019"
  },
  {
    "id": "18",
    "title": "情熱の大阪",
    "artist": "morigasigeru obj.hex",
    "level": "0",
    "md5": "961618e954a9d2e870af548fce62c55f",
    "sha256": "",
    "status": "accepted",
    "datetime": "",
    "proposer": "",
    "comment": "POTY2022"
  },
  {
    "id": "19",
    "title": "俗物フェスティバル -Despair-",
    "artist": "Micelle feat.Yshida / obj:七海",
    "level": "0",
    "md5": "1810130fde5b434f4008a215b57f82cc",
    "sha256": "",
    "status": "accepted",
    "datetime": "",
    "proposer": "",
    "comment": "POTY2022"
  },
  {
    "id": "20",
    "title": "超絶速鍵練習曲第一番「銀世界」",
    "artist": "しらいし / 32 / obj:firi.",
    "level": "0",
    "md5": "540ad15cb16c6a7f4e5f5e3613135bfc",
    "sha256": "",
    "status": "accepted",
    "datetime": "",
    "proposer": "",
    "comment": "POTY2019"
  },
  {
    "id": "246",
    "title": "Materialize Anything [Ground Fissure]",
    "artist": "anubasu-anubasu / obj.7zs",
    "level": "0",
    "md5": "091e742ab34187cb2cc63f461f1a80ca",
    "sha256": "",
    "status": "qualified",
    "datetime": "",
    "proposer": "",
    "comment": ""
  },
  {
    "id": "357",
    "title": "Lewisia",
    "artist": "daiki / BGA:chromato graphy / obj:秘密",
    "level": "0",
    "md5": "eeec3f7659ee455f94e40a1f12645e4e",
    "sha256": "",
    "status": "qualified",
    "datetime": "",
    "proposer": "",
    "comment": ""
  },
  {
    "id": "21",
    "title": "Absolute Future [Fortunately]",
    "artist": "otoshi.b Movie:Arishima_Caprico / obj.mute",
    "level": "1",
    "md5": "792b8daa37dea9193a0e3d92ecc6da75",
    "sha256": "",
    "status": "accepted",
    "datetime": "",
    "proposer": "",
    "comment": "POTY2019"
  },
  {
    "id": "22",
    "title": "BIG CHUNGUS -IR-",
    "artist": "Endigo / チュチャムスメ",
    "level": "1",
    "md5": "dd36e9c11a77222a64e7f4e39deec7a3",
    "sha256": "",
    "status": "accepted",
    "datetime": "",
    "proposer": "",
    "comment": "POTY2021"
  },
  {
    "id": "23",
    "title": "Crazy Watermelon [Pentagon]",
    "artist": "かむちゃうらる obj.hex",
    "level": "1",
    "md5": "949989af49f5de175895edc0e81f832c",
    "sha256": "",
    "status": "accepted",
    "datetime": "",
    "proposer": "",
    "comment": "POTY2022"
  },
  {
    "id": "24",
    "title": "FUELBLOODS (KF)",
    "artist": "callasoiled / obj. AXION",
    "level": "1",
    "md5": "62ee831c874ec747772c86744ed6c7ba",
    "sha256": "",
    "status": "accepted",
    "datetime": "",
    "proposer": "",
    "comment": "POTY2022"
  },
  {
    "id": "25",
    "title": "Shiny☆Strike!!! [Oath to the Future]",
    "artist": "otoshi.b × みゅい × はしたかさん × BAECON",
    "level": "1",
    "md5": "7a7e23eb2a6f734152f520053422e939",
    "sha256": "",
    "status": "accepted",
    "datetime": "",
    "proposer": "",
    "comment": "POTY2021"
  },
  {
    "id": "26",
    "title": "ShootingStar [INFERNO]",
    "artist": "Yu^ta /差分 赤い人",
    "level": "1",
    "md5": "1cb91a4319dce2d1c0971557bbccbddd",
    "sha256": "",
    "status": "qualified",
    "datetime": "",
    "proposer": "",
    "comment": ""
  },
  {
    "id": "27",
    "title": "Tangerine Dawn -IR-",
    "artist": "山田名人 obj.hex",
    "level": "1",
    "md5": "2b6640d408f8a7f10bea55b35d8f82f5",
    "sha256": "",
    "status": "accepted",
    "datetime": "",
    "proposer": "",
    "comment": "POTY2021"
  },
  {
    "id": "28",
    "title": "ゼフィランサス [ANOTHER+]",
    "artist": "2TORI/さ",
    "level": "1",
    "md5": "a997b4d3d0c594fb5f5b09695f1e86df",
    "sha256": "",
    "status": "qualified",
    "datetime": "",
    "proposer": "",
    "comment": ""
  },
  {
    "id": "29",
    "title": "午後のこいしちゃん [EX]",
    "artist": "er/仙人掌の人",
    "level": "1",
    "md5": "ad53525085055d8b1184096eb890be6f",
    "sha256": "",
    "status": "accepted",
    "datetime": "",
    "proposer": "",
    "comment": "POTY2019"
  },
  {
    "id": "244",
    "title": "HOOKER [Gratte Ciel]",
    "artist": "パンダ７７号 / obj.7zs",
    "level": "1",
    "md5": "01e0d67a5ba44cd57168ede127bfba3c",
    "sha256": "",
    "status": "qualified",
    "datetime": "",
    "proposer": "",
    "comment": ""
  },
  {
    "id": "269",
    "title": "FORBIDDEN -ANNIHILATION-",
    "artist": "403 ERROR Image by HEART CREATE / obj:秘密",
    "level": "1",
    "md5": "37bd5d43b121b45c9e6e92723622ed9a",
    "sha256": "",
    "status": "qualified",
    "datetime": "",
    "proposer": "",
    "comment": ""
  },
  {
    "id": "274",
    "title": "new earth [terra nova]",
    "artist": "er obj:HCB",
    "level": "1",
    "md5": "45b002bfe981461be80d75b45df9446f",
    "sha256": "",
    "status": "qualified",
    "datetime": "",
    "proposer": "",
    "comment": ""
  },
  {
    "id": "288",
    "title": "Little Wizard -imaginary satellite-",
    "artist": "Yosk! obj:緒方智絵里 vs 秘密",
    "level": "1",
    "md5": "6907561b925f74064b723122bda63fe5",
    "sha256": "",
    "status": "qualified",
    "datetime": "",
    "proposer": "",
    "comment": ""
  },
  {
    "id": "294",
    "title": "Cutter [Pokapoka Retroad]",
    "artist": "山形まり花 / obj.7zs",
    "level": "1",
    "md5": "7579427e191a4f71f56cc2d027581e15",
    "sha256": "",
    "status": "qualified",
    "datetime": "",
    "proposer": "",
    "comment": ""
  },
  {
    "id": "315",
    "title": "JUMMER -Delayed-",
    "artist": "momo★yama　(BGA:アカツキユウ) obj. BK",
    "level": "1",
    "md5": "ad5917cc6e4c4c681cfc2e91620e3eb8",
    "sha256": "",
    "status": "qualified",
    "datetime": "",
    "proposer": "",
    "comment": ""
  },
  {
    "id": "316",
    "title": "Lieselotte [Hi]",
    "artist": "wa. / deadblue238 / obj:秘密",
    "level": "1",
    "md5": "af28bed2ac56e0fe868b8814aca5f39b",
    "sha256": "",
    "status": "qualified",
    "datetime": "",
    "proposer": "",
    "comment": ""
  },
  {
    "id": "317",
    "title": "hot_coco@ [c@ffe l@tte]",
    "artist": "DJ TAKAHIRO obj.7zs",
    "level": "1",
    "md5": "b0f82b59f9fdaa5b4ac5caa4f973be83",
    "sha256": "",
    "status": "qualified",
    "datetime": "",
    "proposer": "",
    "comment": ""
  },
  {
    "id": "333",
    "title": "風の塔 [Sky Tower]",
    "artist": "しも fw. hapi⇒ / obj.Waddle Dee",
    "level": "1",
    "md5": "ca3ce7901befff9ab4d3aeb77b9359a6",
    "sha256": "",
    "status": "qualified",
    "datetime": "",
    "proposer": "",
    "comment": ""
  },
  {
    "id": "30",
    "title": "Air -HADES-",
    "artist": "SHIKI / po",
    "level": "2",
    "md5": "a28a3fbcc2bfd8c8516e78e3aacbdbbc",
    "sha256": "",
    "status": "qualified",
    "datetime": "",
    "proposer": "",
    "comment": ""
  },
  {
    "id": "31",
    "title": "B e l i - R - G O D",
    "artist": "+45 / obj: white train",
    "level": "2",
    "md5": "91b0a169e6cde78b058fda8a404240a0",
    "sha256": "",
    "status": "qualified",
    "datetime": "",
    "proposer": "",
    "comment": ""
  },
  {
    "id": "32",
    "title": "black opal [Pentagon]",
    "artist": "TAK vs General / Jeff obj.hex",
    "level": "2",
    "md5": "0d6e7a4bb86fc4019f91e177309c1d61",
    "sha256": "",
    "status": "qualified",
    "datetime": "",
    "proposer": "",
    "comment": ""
  },
  {
    "id": "33",
    "title": "Critical Cannonball -Xe-",
    "artist": "SEPHID mov LankaNIK / obj : LindBlum",
    "level": "2",
    "md5": "e065513d6b16c941c9d540e2cf20d7d7",
    "sha256": "",
    "status": "qualified",
    "datetime": "",
    "proposer": "",
    "comment": ""
  },
  {
    "id": "34",
    "title": "dreamin' -happycore version - [INFERNO]",
    "artist": "AOiRO_Manbow with kagerow/ 差分 赤い人",
    "level": "2",
    "md5": "960d994d0f433ba8c1806f6cb442b9ea",
    "sha256": "",
    "status": "qualified",
    "datetime": "",
    "proposer": "",
    "comment": ""
  },
  {
    "id": "35",
    "title": "Lapis -The Heavens Remix- [Reminiscence]",
    "artist": "arranged by Yamajet obj : LindBlum",
    "level": "2",
    "md5": "035eec9c7964ebea27c4163def2453d1",
    "sha256": "",
    "status": "accepted",
    "datetime": "",
    "proposer": "",
    "comment": "POTY2022"
  },
  {
    "id": "36",
    "title": "Love & Justice [7KEYS 修羅BEGINNER]",
    "artist": "フロン / ラズベリル / obj:夢瑠",
    "level": "2",
    "md5": "e8c1f79feb118c4078c993ff89595733",
    "sha256": "",
    "status": "qualified",
    "datetime": "",
    "proposer": "",
    "comment": ""
  },
  {
    "id": "37",
    "title": "Ms. Steam [Hexagon]",
    "artist": "MoVIIkA Movie: Nao_AnD / obj.hex",
    "level": "2",
    "md5": "45b6a94349443e21fcc2b9c542c1fe50",
    "sha256": "",
    "status": "accepted",
    "datetime": "",
    "proposer": "",
    "comment": "POTY2022"
  },
  {
    "id": "38",
    "title": "NS22 [Snother]",
    "artist": "3034 obj:スノート",
    "level": "2",
    "md5": "dc0c62e5c809c1a75460edb5f4640006",
    "sha256": "",
    "status": "accepted",
    "datetime": "",
    "proposer": "",
    "comment": "POTY2019"
  },
  {
    "id": "39",
    "title": "Psalms ～魂の還るばしょ～ [ANGELUS]",
    "artist": "qfeileadh＆レゾナンスもえこ mov:Maeus",
    "level": "2",
    "md5": "4709c903d17c408695c131d230c20dc5",
    "sha256": "",
    "status": "accepted",
    "datetime": "",
    "proposer": "",
    "comment": "POTY2021"
  },
  {
    "id": "41",
    "title": "Snowdrop -Eclipse-",
    "artist": "urimu Movie:inukoro / selene.",
    "level": "2",
    "md5": "31ff65a41882c20e443b78b5801b35c2",
    "sha256": "",
    "status": "qualified",
    "datetime": "",
    "proposer": "",
    "comment": ""
  },
  {
    "id": "42",
    "title": "Ultimate radiation",
    "artist": "sun3/ds",
    "level": "2",
    "md5": "e4cfef6f66822ede926b39b93f7f3dbb",
    "sha256": "",
    "status": "qualified",
    "datetime": "",
    "proposer": "",
    "comment": ""
  },
  {
    "id": "43",
    "title": "Unshakable -Zen-",
    "artist": "RiraN movie : Irelriser",
    "level": "2",
    "md5": "96c017e393898a99000ecbd2c3ae80ac",
    "sha256": "",
    "status": "accepted",
    "datetime": "",
    "proposer": "",
    "comment": "POTY2019"
  },
  {
    "id": "44",
    "title": "Valkyrie Revolutia [Hexagon]",
    "artist": "Sakamiya obj.hex",
    "level": "2",
    "md5": "d0c19223794014a1e8686e70350d2cd2",
    "sha256": "",
    "status": "qualified",
    "datetime": "",
    "proposer": "",
    "comment": ""
  },
  {
    "id": "45",
    "title": "yksinaisyys [Gehenna]",
    "artist": "Le Dos-on / obj:秘密 bga : Air",
    "level": "2",
    "md5": "5713095faa7f7801eb9624e4a693e077",
    "sha256": "",
    "status": "qualified",
    "datetime": "",
    "proposer": "",
    "comment": ""
  },
  {
    "id": "46",
    "title": "カタバミ [CLOVER]",
    "artist": "qfeileadh",
    "level": "2",
    "md5": "d81df4fcdc04d38a65c948a95a30911f",
    "sha256": "",
    "status": "accepted",
    "datetime": "",
    "proposer": "",
    "comment": "POTY2021"
  },
  {
    "id": "47",
    "title": "ハッピーフェイクショー [Haven't you heard?]",
    "artist": "Ponchi♪ feat.はぁち obj.nozomi",
    "level": "2",
    "md5": "196b23d514f7831e2c40f094a23e476e",
    "sha256": "",
    "status": "accepted",
    "datetime": "",
    "proposer": "",
    "comment": "POTY2022"
  },
  {
    "id": "48",
    "title": "マッドメチャクチャニズム [INSANE]",
    "artist": "69 de 74 BGI:れおん",
    "level": "2",
    "md5": "d415aa79f5fbd7f1a1944146afd5f9af",
    "sha256": "",
    "status": "accepted",
    "datetime": "",
    "proposer": "",
    "comment": "POTY2019"
  },
  {
    "id": "50",
    "title": "壊廊 [Pentagon]",
    "artist": "Ice Plumes obj.hex",
    "level": "2",
    "md5": "9dbe683eadf8d92a525bab680b0b4228",
    "sha256": "",
    "status": "qualified",
    "datetime": "",
    "proposer": "",
    "comment": ""
  },
  {
    "id": "51",
    "title": "玉響サーチライト [Little Little Unisons]",
    "artist": "otoshi.b × みゅい & tolz × はしたかさん & mute",
    "level": "2",
    "md5": "60bc96c61bfc3d42c765ddb329a79b9c",
    "sha256": "",
    "status": "accepted",
    "datetime": "",
    "proposer": "",
    "comment": "POTY2022"
  },
  {
    "id": "52",
    "title": "秩序の秋桜 [ありがたや+]",
    "artist": "くっちー obj:yutaka Movie:HEART CREATE",
    "level": "2",
    "md5": "7ccfccdea1b8d4c3dc7691a55649ec15",
    "sha256": "",
    "status": "qualified",
    "datetime": "",
    "proposer": "",
    "comment": ""
  },
  {
    "id": "53",
    "title": "天空の城ヴェリエル [SABOTHER]",
    "artist": "うえつ氏 /さ",
    "level": "2",
    "md5": "fb975909eb0f60a9190c7a1007515d4b",
    "sha256": "",
    "status": "qualified",
    "datetime": "",
    "proposer": "",
    "comment": ""
  },
  {
    "id": "54",
    "title": "白の魔法の光 (LHGOD-)",
    "artist": "こどものなみだ / BANZAI",
    "level": "2",
    "md5": "6ea26b0431e3d78d36a07055d80c2c0d",
    "sha256": "",
    "status": "qualified",
    "datetime": "",
    "proposer": "",
    "comment": ""
  },
  {
    "id": "55",
    "title": "杪冬の願い [CONNECT]",
    "artist": "あとぅす feat.橘花音 BGI:りーふぱいザウルス",
    "level": "2",
    "md5": "9076c384d78d4b5f77a2517a7b06e506",
    "sha256": "",
    "status": "accepted",
    "datetime": "",
    "proposer": "",
    "comment": "POTY2022"
  },
  {
    "id": "255",
    "title": "Anzu no Kakkoi Ongaku [Lazy Fairy]",
    "artist": "Futaba Anzu / obj.7zs",
    "level": "2",
    "md5": "15c5a73ae1d51dbce821a76cc3bd8232",
    "sha256": "",
    "status": "qualified",
    "datetime": "",
    "proposer": "",
    "comment": ""
  },
  {
    "id": "285",
    "title": "Reason [ινσανε]",
    "artist": "Juno BGI : Sierra obj:秘密 vs chack",
    "level": "2",
    "md5": "67b038af314de078e9c58806dc208e37",
    "sha256": "",
    "status": "qualified",
    "datetime": "",
    "proposer": "",
    "comment": ""
  },
  {
    "id": "314",
    "title": "TwoPhace [Double Dealer]",
    "artist": "litmus* + Sound Souler / obj.7zs mov : Khronetic",
    "level": "2",
    "md5": "aa8075a675ecaaeb33902932bcd69406",
    "sha256": "",
    "status": "qualified",
    "datetime": "",
    "proposer": "",
    "comment": ""
  },
  {
    "id": "318",
    "title": "Black Lotus -PUNISHMENT-",
    "artist": "wa. / 百舌谷 obj. B_K",
    "level": "2",
    "md5": "b3ac65351c03998e3276790503008d46",
    "sha256": "",
    "status": "qualified",
    "datetime": "",
    "proposer": "",
    "comment": ""
  },
  {
    "id": "56",
    "title": "+84 [+200]",
    "artist": "はがね / И",
    "level": "3",
    "md5": "2ae6ffab1595e4164ff098a190e6e0f1",
    "sha256": "",
    "status": "qualified",
    "datetime": "",
    "proposer": "",
    "comment": ""
  },
  {
    "id": "58",
    "title": "★SweeT DiscoverY★ -Be HappY!-",
    "artist": "chocolate max obj:otoshi.b",
    "level": "3",
    "md5": "adb8fe149acde030640503371a58c760",
    "sha256": "",
    "status": "qualified",
    "datetime": "",
    "proposer": "",
    "comment": ""
  },
  {
    "id": "59",
    "title": "7SP:雪の少女-MorningDash!Mix- [GOD]",
    "artist": "猫蟹丸 / obj: black train",
    "level": "3",
    "md5": "d06f7121bc12c8bdab9097c936d84ba9",
    "sha256": "",
    "status": "qualified",
    "datetime": "",
    "proposer": "",
    "comment": ""
  },
  {
    "id": "60",
    "title": "Angel's Salad [REALISM]",
    "artist": "かたぎり BGA: 2nd_identity (mst×かたぎり) OBJ: LuvTek",
    "level": "3",
    "md5": "02fd0a7beaded078d6c68ae4480c5908",
    "sha256": "",
    "status": "accepted",
    "datetime": "",
    "proposer": "",
    "comment": "POTY2020"
  },
  {
    "id": "61",
    "title": "APOLLON [GOD]",
    "artist": "sun3 / Add Sounds:??? / obj. AXION",
    "level": "3",
    "md5": "9b31cd0943d3824d8b50de1f9d08319b",
    "sha256": "",
    "status": "accepted",
    "datetime": "",
    "proposer": "",
    "comment": "POTY2022"
  },
  {
    "id": "62",
    "title": "CODE-F -soar to the Frontier- [地力]",
    "artist": "kei iwata/obj:Charlotte.",
    "level": "3",
    "md5": "0638c5aaa79a3d748eb6d49f9d6ad1b2",
    "sha256": "",
    "status": "qualified",
    "datetime": "",
    "proposer": "",
    "comment": ""
  },
  {
    "id": "63",
    "title": "Destroyer［Oxygen］",
    "artist": "Tlahuizcalpantecuhtli BGA: Air OBJ : ランダマイザ",
    "level": "3",
    "md5": "3216e0be0404e5311672194432d8b82a",
    "sha256": "",
    "status": "qualified",
    "datetime": "",
    "proposer": "",
    "comment": ""
  },
  {
    "id": "64",
    "title": "DEYANEN [Hexagon]",
    "artist": "アスパラ音楽隊 obj.hex",
    "level": "3",
    "md5": "9cd5a316117bce74196a4fc94d56e39c",
    "sha256": "",
    "status": "accepted",
    "datetime": "",
    "proposer": "",
    "comment": "POTY2021"
  },
  {
    "id": "65",
    "title": "Drop Down [stand alone]",
    "artist": "LunaticSounds / ShiginoEicar OBJ : ランダマイザ",
    "level": "3",
    "md5": "72eb962296d74fa32fa0dd32a17369e8",
    "sha256": "",
    "status": "qualified",
    "datetime": "",
    "proposer": "",
    "comment": ""
  },
  {
    "id": "66",
    "title": "Endless Dream -Reminiscence-",
    "artist": "SHIKI // BGA:あかくらげ & M.H / selene.",
    "level": "3",
    "md5": "9537a84edc60f14997d57061e16107e5",
    "sha256": "",
    "status": "qualified",
    "datetime": "",
    "proposer": "",
    "comment": ""
  },
  {
    "id": "67",
    "title": "Endless Dream -Zero Dimensions-",
    "artist": "SHIKI / obj:DDX",
    "level": "3",
    "md5": "d012f9fbe125aa49e48755ea4fbbb1db",
    "sha256": "",
    "status": "qualified",
    "datetime": "",
    "proposer": "",
    "comment": ""
  },
  {
    "id": "68",
    "title": "F13 [つよい]",
    "artist": "Judah BGA:Lucifer",
    "level": "3",
    "md5": "a9375e12d23080e77fb58f717eeb5c9e",
    "sha256": "",
    "status": "qualified",
    "datetime": "",
    "proposer": "",
    "comment": ""
  },
  {
    "id": "69",
    "title": "far in the blue sky... [remember...]",
    "artist": "saikoro",
    "level": "3",
    "md5": "7aa7e173c7ef7464579c513b74a08d7a",
    "sha256": "",
    "status": "accepted",
    "datetime": "",
    "proposer": "",
    "comment": "POTY2020"
  },
  {
    "id": "70",
    "title": "FREEDOM DiVE [UNIVERSE]",
    "artist": "xi / air",
    "level": "3",
    "md5": "2e2c4168d3c350de3136a0c2ad23dce3",
    "sha256": "",
    "status": "qualified",
    "datetime": "",
    "proposer": "",
    "comment": ""
  },
  {
    "id": "71",
    "title": "Funky Anthem \"F\" [SP INSANE]",
    "artist": "hayato87b obj: air",
    "level": "3",
    "md5": "ff8b3ddd39a2963428a11d3f68b2aa0f",
    "sha256": "",
    "status": "qualified",
    "datetime": "",
    "proposer": "",
    "comment": ""
  },
  {
    "id": "72",
    "title": "Icicle Stinger [反逆の月]",
    "artist": "ROKINA / obj:スノート BGA:出前",
    "level": "3",
    "md5": "cc46defcf924610674964ebf4f7acaaa",
    "sha256": "",
    "status": "accepted",
    "datetime": "",
    "proposer": "",
    "comment": "POTY2019"
  },
  {
    "id": "73",
    "title": "Illusion of Mind [kerother]",
    "artist": "P4koo / OBJ:けろささ",
    "level": "3",
    "md5": "24ffc0e42b4c0aa1b7f43232e777201b",
    "sha256": "",
    "status": "qualified",
    "datetime": "",
    "proposer": "",
    "comment": ""
  },
  {
    "id": "74",
    "title": "Jack in the Vox [Pentagon]",
    "artist": "MONO obj.hex",
    "level": "3",
    "md5": "aa18cd83e9bd14cade78cad49d14d4f1",
    "sha256": "",
    "status": "qualified",
    "datetime": "",
    "proposer": "",
    "comment": ""
  },
  {
    "id": "75",
    "title": "kkotipari Hangaduk [INFERNO]",
    "artist": "bbangsami feat.Sugar Reactor / Haping,SMIN/ 差分　赤い人",
    "level": "3",
    "md5": "61f0a8ab27a5d675b2abac437e122ad4",
    "sha256": "",
    "status": "qualified",
    "datetime": "",
    "proposer": "",
    "comment": ""
  },
  {
    "id": "76",
    "title": "NightTheater [FishLife]",
    "artist": "わかどり BGA : もがみ / obj:th",
    "level": "3",
    "md5": "c9ffe8fa9d5000b3f5a734216487270c",
    "sha256": "",
    "status": "accepted",
    "datetime": "",
    "proposer": "",
    "comment": "POTY2021"
  },
  {
    "id": "77",
    "title": "on the sequence #3 [Apocalypsis]",
    "artist": "6yen / И",
    "level": "3",
    "md5": "83da3c5e8ab72154a4bcdcd139bdb86f",
    "sha256": "",
    "status": "qualified",
    "datetime": "",
    "proposer": "",
    "comment": ""
  },
  {
    "id": "78",
    "title": "Paraclete [INFELNO]",
    "artist": "LeaF/差分　赤い人",
    "level": "3",
    "md5": "8ad0e0556389b7fab8883a6fd5e1c042",
    "sha256": "",
    "status": "qualified",
    "datetime": "",
    "proposer": "",
    "comment": ""
  },
  {
    "id": "79",
    "title": "Rainy Gate [Squall]",
    "artist": "E0ri4 BGA:GAMEBAKA / obj:Guanacoite",
    "level": "3",
    "md5": "a726522ecd7b6599e9e652f76c9540d1",
    "sha256": "",
    "status": "qualified",
    "datetime": "",
    "proposer": "",
    "comment": ""
  },
  {
    "id": "80",
    "title": "Replica -LAST BOSS-",
    "artist": "Lime",
    "level": "3",
    "md5": "8a42ff125b65390de1a2fd957dec2106",
    "sha256": "",
    "status": "accepted",
    "datetime": "",
    "proposer": "",
    "comment": "POTY2019"
  },
  {
    "id": "81",
    "title": "Rin-Rin [7K LT's INSANE]",
    "artist": "Hyparpax obj: LuvTek",
    "level": "3",
    "md5": "6055fa88e9f0ca8642d88b75f2808e1d",
    "sha256": "",
    "status": "accepted",
    "datetime": "",
    "proposer": "",
    "comment": "POTY2021"
  },
  {
    "id": "82",
    "title": "Time files [GOD]",
    "artist": "xi / obj:BAECON",
    "level": "3",
    "md5": "cbd09eb559169246ba03cbda820c48ef",
    "sha256": "",
    "status": "qualified",
    "datetime": "",
    "proposer": "",
    "comment": ""
  },
  {
    "id": "83",
    "title": "tinnitus [load]",
    "artist": "SP-# / obj.fuko",
    "level": "3",
    "md5": "ff52797ef9b4e23b460228e374524a6f",
    "sha256": "",
    "status": "qualified",
    "datetime": "",
    "proposer": "",
    "comment": ""
  },
  {
    "id": "84",
    "title": "Twin☆kle Galaxies [Journey 2 Sparkling Galaxies!!]",
    "artist": "翡乃イスカ × otoshi.b BGI : 幸健兎 × はしたかさん / obj : BAECON",
    "level": "3",
    "md5": "a03bfdf932e76f4c23e3b0628a301781",
    "sha256": "",
    "status": "accepted",
    "datetime": "",
    "proposer": "",
    "comment": "POTY2020"
  },
  {
    "id": "85",
    "title": "アルスノヴァに喝采を [ANGUISHFUL]",
    "artist": "qfeileadh feat.レゾナンスもえこ movie:アカイユウ / illust:ねるぞう",
    "level": "3",
    "md5": "2192cc7b27d7afad57a2aba085f94b2f",
    "sha256": "",
    "status": "accepted",
    "datetime": "",
    "proposer": "",
    "comment": "POTY2022"
  },
  {
    "id": "86",
    "title": "ウタカタ・サマーメモリーズ -To The Future-",
    "artist": "kei_iwata feat.レゾナンスもえこ obj:七海 Movie:Arishima_Caprico Illust:Morph",
    "level": "3",
    "md5": "e9fc82f22a048d62165c482841eb0d33",
    "sha256": "",
    "status": "accepted",
    "datetime": "",
    "proposer": "",
    "comment": "POTY2020"
  },
  {
    "id": "87",
    "title": "ゴクラクハスノウテナ (EX)",
    "artist": "Luv Strawberry's Delta",
    "level": "3",
    "md5": "f0369b6ad8cbebd6c8057b826abd77cf",
    "sha256": "",
    "status": "qualified",
    "datetime": "",
    "proposer": "",
    "comment": ""
  },
  {
    "id": "89",
    "title": "ちんこ音頭2022 [フィジカル横チン識]",
    "artist": "くっちー obj:垢伴次郎",
    "level": "3",
    "md5": "baf435b1b3ceab8cba39e58bf86b30de",
    "sha256": "",
    "status": "accepted",
    "datetime": "",
    "proposer": "",
    "comment": "POTY2022"
  },
  {
    "id": "90",
    "title": "フロンティア↑↑エクスプローラー [UNIVERSE]",
    "artist": "kei_iwata Illust:morph/ BGA&obj:qfeileadh",
    "level": "3",
    "md5": "68c58f701bf7317c934c9019299be170",
    "sha256": "",
    "status": "accepted",
    "datetime": "",
    "proposer": "",
    "comment": "POTY2020"
  },
  {
    "id": "91",
    "title": "ミライトコネクト [rumther]",
    "artist": "Sound piercer & ginkiha (feat.柚子花 & NeLiME) obj:西京極ラム子",
    "level": "3",
    "md5": "b8792b87c09dcb065fff1571807ca5b3",
    "sha256": "",
    "status": "qualified",
    "datetime": "",
    "proposer": "",
    "comment": ""
  },
  {
    "id": "92",
    "title": "絵空事の世界と私　 [EX]",
    "artist": "イヴ/さ",
    "level": "3",
    "md5": "d324f981955e881393501f0f791b2d93",
    "sha256": "",
    "status": "qualified",
    "datetime": "",
    "proposer": "",
    "comment": ""
  },
  {
    "id": "93",
    "title": "確固たる意志 [INFERNO]",
    "artist": "69 de 74 BGA : EViL/obj:赤い人",
    "level": "3",
    "md5": "149da54b5d789855bdfa3692c026b3e3",
    "sha256": "",
    "status": "qualified",
    "datetime": "",
    "proposer": "",
    "comment": ""
  },
  {
    "id": "94",
    "title": "水晶世界 ～Fracture～ [GOD]",
    "artist": "秋山 澪 / obj:BAECON",
    "level": "3",
    "md5": "1758f4f1386835265fdf8dbb6f6ffb4f",
    "sha256": "",
    "status": "qualified",
    "datetime": "",
    "proposer": "",
    "comment": ""
  },
  {
    "id": "95",
    "title": "俗物フェスティバル [无何之郷]",
    "artist": "Micelle feat.Yshida / obj:Lian",
    "level": "3",
    "md5": "f19e43deacedd0cd190ce7aa75c67479",
    "sha256": "",
    "status": "accepted",
    "datetime": "",
    "proposer": "",
    "comment": "POTY2022"
  },
  {
    "id": "260",
    "title": "Empress of Raizze [フルマラソン]",
    "artist": "-45/わなな・BANI / obj:発汗BMS",
    "level": "3",
    "md5": "28de731d48217bbd50f49b1ad572f81f",
    "sha256": "",
    "status": "qualified",
    "datetime": "",
    "proposer": "",
    "comment": ""
  },
  {
    "id": "97",
    "title": "A [n/a]",
    "artist": "裏吉川 obj:垢伴次郎",
    "level": "4",
    "md5": "811b3dde7cc6da2d7ede3a7dc523515b",
    "sha256": "",
    "status": "accepted",
    "datetime": "",
    "proposer": "",
    "comment": "POTY2022"
  },
  {
    "id": "98",
    "title": "Absolute Future [Infinity]",
    "artist": "otoshi.b Movie:Arishima_Caprico / obj.mute",
    "level": "4",
    "md5": "2b5c45cbbe5ce2539c8548d5d523e11f",
    "sha256": "",
    "status": "qualified",
    "datetime": "",
    "proposer": "",
    "comment": ""
  },
  {
    "id": "99",
    "title": "Astraia [ELITHER]",
    "artist": "Azel obj:ELIGOS",
    "level": "4",
    "md5": "45b0c4ac043def235539842d12765dbe",
    "sha256": "",
    "status": "qualified",
    "datetime": "",
    "proposer": "",
    "comment": ""
  },
  {
    "id": "100",
    "title": "Blooming Jump! [Maneuver]",
    "artist": "卯月 改",
    "level": "4",
    "md5": "161d264c8c0b2c554ddf382713d5dc68",
    "sha256": "",
    "status": "qualified",
    "datetime": "",
    "proposer": "",
    "comment": ""
  },
  {
    "id": "101",
    "title": "Calamity Fortune [INFERNO]",
    "artist": "ZUN remixed by LeaF/ 差分 赤い人 Movie:Optie",
    "level": "4",
    "md5": "096087f9fec3c8f065912682314e3496",
    "sha256": "",
    "status": "qualified",
    "datetime": "",
    "proposer": "",
    "comment": ""
  },
  {
    "id": "103",
    "title": "DUARRIER [Twin Stream]",
    "artist": "Nuekawa obj: qtp13",
    "level": "4",
    "md5": "8b312d3e85bbae454ba7c5bd76cbe706",
    "sha256": "",
    "status": "qualified",
    "datetime": "",
    "proposer": "",
    "comment": ""
  },
  {
    "id": "104",
    "title": "Evoltex [Eventual Epoch]",
    "artist": "Arch movie:Roaring Flame obj:Guanacoite",
    "level": "4",
    "md5": "1224830aeab9f9e0a8c967a19b04d4bb",
    "sha256": "",
    "status": "qualified",
    "datetime": "",
    "proposer": "",
    "comment": ""
  },
  {
    "id": "105",
    "title": "FAKE LIFE [Nihilism]",
    "artist": "ProjectG obj. T",
    "level": "4",
    "md5": "68f709ad576392f57fcbee4b0df88fe3",
    "sha256": "",
    "status": "accepted",
    "datetime": "",
    "proposer": "",
    "comment": "POTY2021"
  },
  {
    "id": "107",
    "title": "Fluctuate [Pentagon]",
    "artist": "ALFOU obj.hex",
    "level": "4",
    "md5": "6d8ec35af7fbd1647cfabdde5a9fc75f",
    "sha256": "",
    "status": "qualified",
    "datetime": "",
    "proposer": "",
    "comment": ""
  },
  {
    "id": "108",
    "title": "Grimoire Judgment -Eclipse-",
    "artist": "Namiel BGI：グーラン / selene.",
    "level": "4",
    "md5": "34bd456aae9005cecc7c6065caaa77b4",
    "sha256": "",
    "status": "qualified",
    "datetime": "",
    "proposer": "",
    "comment": ""
  },
  {
    "id": "109",
    "title": "Happy Ending Story☆ -TrueEND-",
    "artist": "ROKINA あ",
    "level": "4",
    "md5": "515ef0685a13ed7432702bde38011112",
    "sha256": "",
    "status": "qualified",
    "datetime": "",
    "proposer": "",
    "comment": ""
  },
  {
    "id": "110",
    "title": "Head BONK ache [CLUSTER HEADACHE]",
    "artist": "saaa ft. MC iwata Bros. / BGA : 空読無 白眼",
    "level": "4",
    "md5": "1582787258f430961e6a3245454def5b",
    "sha256": "",
    "status": "accepted",
    "datetime": "",
    "proposer": "",
    "comment": "POTY2022"
  },
  {
    "id": "111",
    "title": "hurt, scenery, groundrainbow [Beautiful Scenery]",
    "artist": "syatten + coda Sliced by bms newbie",
    "level": "4",
    "md5": "d26e5a64c2527b7268ce450cc99700c4",
    "sha256": "",
    "status": "accepted",
    "datetime": "",
    "proposer": "",
    "comment": "POTY2020"
  },
  {
    "id": "112",
    "title": "Intercosmic travel [cosmos]",
    "artist": "Mr.Faine",
    "level": "4",
    "md5": "5a1ba2cd11aae96fbc7268c19345cec7",
    "sha256": "",
    "status": "qualified",
    "datetime": "",
    "proposer": "",
    "comment": ""
  },
  {
    "id": "113",
    "title": "It's \"alice\" dream [I want to be...]",
    "artist": "polysha / obj : LindBlum",
    "level": "4",
    "md5": "4e75cccd709eba514c0bb962d823ca89",
    "sha256": "",
    "status": "qualified",
    "datetime": "",
    "proposer": "",
    "comment": ""
  },
  {
    "id": "114",
    "title": "LAST PROPOZE [Farewell]",
    "artist": "あとぅす feat.橘花音 BGI:りーふぱいザウルス obj : BAECON",
    "level": "4",
    "md5": "59ee16a8325b5fc5978f1e465b76d844",
    "sha256": "",
    "status": "accepted",
    "datetime": "",
    "proposer": "",
    "comment": "POTY2021"
  },
  {
    "id": "115",
    "title": "Let me wish shooting star -Genocide-",
    "artist": "RSK / selene.",
    "level": "4",
    "md5": "2e088b5613507357a9fe5496b4eb187d",
    "sha256": "",
    "status": "qualified",
    "datetime": "",
    "proposer": "",
    "comment": ""
  },
  {
    "id": "116",
    "title": "Lethal Strike [DENIAL]",
    "artist": "Lian",
    "level": "4",
    "md5": "6edb09c73a5d5296af82ea181a612aa3",
    "sha256": "",
    "status": "qualified",
    "datetime": "",
    "proposer": "",
    "comment": ""
  },
  {
    "id": "117",
    "title": "Levitation [Pentagon]",
    "artist": "TAK / 140 obj.hex",
    "level": "4",
    "md5": "e96936e8020f18571103ef7259f4b138",
    "sha256": "",
    "status": "qualified",
    "datetime": "",
    "proposer": "",
    "comment": ""
  },
  {
    "id": "118",
    "title": "Ophelia [Extreme]",
    "artist": "Lime",
    "level": "4",
    "md5": "9dd20fc49c9a5f5ce9cd6ac5fdb3e68c",
    "sha256": "",
    "status": "qualified",
    "datetime": "",
    "proposer": "",
    "comment": ""
  },
  {
    "id": "119",
    "title": "reAdvenTia [Hexagon]",
    "artist": "daisan obj.hex",
    "level": "4",
    "md5": "bae134c66f0654a801dd832a799ac822",
    "sha256": "",
    "status": "qualified",
    "datetime": "",
    "proposer": "",
    "comment": ""
  },
  {
    "id": "120",
    "title": "S.Q.4.D.",
    "artist": "牧野 obj. LuvTek",
    "level": "4",
    "md5": "c50917f41ef776188f0269304af29692",
    "sha256": "",
    "status": "accepted",
    "datetime": "",
    "proposer": "",
    "comment": "POTY2022"
  },
  {
    "id": "121",
    "title": "SpaceScape [Triangle]",
    "artist": "wellow / obj.ぶんぺ～",
    "level": "4",
    "md5": "3db1ad8f869365dc33ed1137a5bb79e4",
    "sha256": "",
    "status": "qualified",
    "datetime": "",
    "proposer": "",
    "comment": ""
  },
  {
    "id": "122",
    "title": "SpringField [end of spring]",
    "artist": "QH. obj: 今村水産市場",
    "level": "4",
    "md5": "ecc9599a609c07acab922341013f7c3d",
    "sha256": "",
    "status": "qualified",
    "datetime": "",
    "proposer": "",
    "comment": ""
  },
  {
    "id": "123",
    "title": "Synthesized Girl's Heart [EX]",
    "artist": "SHIKI obj:tamate",
    "level": "4",
    "md5": "323f8db6c78c71241c433bf40af45128",
    "sha256": "",
    "status": "qualified",
    "datetime": "",
    "proposer": "",
    "comment": ""
  },
  {
    "id": "124",
    "title": "TearVid [Other]",
    "artist": "An obj:Omino",
    "level": "4",
    "md5": "575a09f7bd5d6e22f91e01fdff83ff38",
    "sha256": "",
    "status": "accepted",
    "datetime": "",
    "proposer": "",
    "comment": "POTY2020"
  },
  {
    "id": "125",
    "title": "The Last Page -LAST BOSS-",
    "artist": "ARForest / inukoro",
    "level": "4",
    "md5": "bd2326f72f9586eb13f5f4f9d202ade2",
    "sha256": "",
    "status": "accepted",
    "datetime": "",
    "proposer": "",
    "comment": "POTY2020"
  },
  {
    "id": "126",
    "title": "tinnitus -Genocide-",
    "artist": "SP-# / selene.",
    "level": "4",
    "md5": "d49874c9835571a8d892e6ed6a0dcaef",
    "sha256": "",
    "status": "qualified",
    "datetime": "",
    "proposer": "",
    "comment": ""
  },
  {
    "id": "127",
    "title": "VENDeTTA [Un diavolo scaccia l'atro]",
    "artist": "Cataclysmic Order BGI:FARNA obj.nozomi",
    "level": "4",
    "md5": "feff7bff7a1555e99dc1d8c754a894b4",
    "sha256": "",
    "status": "accepted",
    "datetime": "",
    "proposer": "",
    "comment": "POTY2022"
  },
  {
    "id": "128",
    "title": "Volt [Maryther]",
    "artist": "utah / obj: Mary_Sue",
    "level": "4",
    "md5": "ee24c4fe2e7784fa46b87d905da6df32",
    "sha256": "",
    "status": "qualified",
    "datetime": "",
    "proposer": "",
    "comment": ""
  },
  {
    "id": "129",
    "title": "Wonder World! (GOD)",
    "artist": "kagerow",
    "level": "4",
    "md5": "aa4279b54d8ffbd8f8f6f5ebf228d83a",
    "sha256": "",
    "status": "qualified",
    "datetime": "",
    "proposer": "",
    "comment": ""
  },
  {
    "id": "130",
    "title": "ロッカー -SchooL-",
    "artist": "ATEMAK / obj:GN",
    "level": "4",
    "md5": "19ff31a22c82c8a99b0fe36c108116c0",
    "sha256": "",
    "status": "qualified",
    "datetime": "",
    "proposer": "",
    "comment": ""
  },
  {
    "id": "131",
    "title": "花たちに希望を [akather]",
    "artist": "Sound piercer feat.DAZBEE NeLiME / CHERISH / fxxh / Feyrlin obj.akasaka",
    "level": "4",
    "md5": "4dfe267c203adc4d98989ccebd66271c",
    "sha256": "",
    "status": "qualified",
    "datetime": "",
    "proposer": "",
    "comment": ""
  },
  {
    "id": "132",
    "title": "壊廊 [Hexagon]",
    "artist": "Ice Plumes obj.hex",
    "level": "4",
    "md5": "82c1314cf8ab2c96321aaf67eb16c83c",
    "sha256": "",
    "status": "accepted",
    "datetime": "",
    "proposer": "",
    "comment": "POTY2020"
  },
  {
    "id": "133",
    "title": "失望Choco (・∀・)",
    "artist": "LeaF/さ",
    "level": "4",
    "md5": "b55dfab33a7a018c30bd82ae42b0369c",
    "sha256": "",
    "status": "qualified",
    "datetime": "",
    "proposer": "",
    "comment": ""
  },
  {
    "id": "134",
    "title": "宵桜回廊 [狂]",
    "artist": "佐久丸(sak vs wumalutsufuri) obj:sak",
    "level": "4",
    "md5": "44a242e411cb99e924b26cfa342413f1",
    "sha256": "",
    "status": "accepted",
    "datetime": "",
    "proposer": "",
    "comment": "POTY2019"
  },
  {
    "id": "135",
    "title": "織姫(Independent from God, Everlasting love remix) [gratitude]",
    "artist": "DJ TAKUAN 及び 佐倉アヤキ remixed by uet BGI:いかお / obj : BAECON",
    "level": "4",
    "md5": "8244df1b6371ba82d8cf3c2374d3b91a",
    "sha256": "",
    "status": "qualified",
    "datetime": "",
    "proposer": "",
    "comment": ""
  },
  {
    "id": "136",
    "title": "雪の少女-MorningDash!Mix- [RuNRuN-EX]",
    "artist": "猫蟹丸(obj.WAS)",
    "level": "4",
    "md5": "bb1f191526ff2ae97fdf274ca33873b8",
    "sha256": "",
    "status": "qualified",
    "datetime": "",
    "proposer": "",
    "comment": ""
  },
  {
    "id": "137",
    "title": "日溜りの街－あ！－ (HELL)",
    "artist": "猫蟹丸 / obj: black train",
    "level": "4",
    "md5": "6b607db3717c41e13d778c83692ba66d",
    "sha256": "",
    "status": "qualified",
    "datetime": "",
    "proposer": "",
    "comment": ""
  },
  {
    "id": "138",
    "title": "風時夏 [夏海記]",
    "artist": "otoshi.b BGI:鈴木なるひ obj:BAECON",
    "level": "4",
    "md5": "77b284df71745b66f94e71db50961b3b",
    "sha256": "",
    "status": "accepted",
    "datetime": "",
    "proposer": "",
    "comment": "POTY2022"
  },
  {
    "id": "139",
    "title": "腹腹時計",
    "artist": "Aozuna obj:???",
    "level": "4",
    "md5": "4076708c5cc91788f2ffcf65c72a4073",
    "sha256": "",
    "status": "qualified",
    "datetime": "",
    "proposer": "",
    "comment": ""
  },
  {
    "id": "214",
    "title": "玉響サーチライト [陽溜ファーストステップ]",
    "artist": "otoshi.b × みゅい & tolz × はしたかさん & BAECON",
    "level": "4",
    "md5": "5bec55352a1e9c1ae777c8fd43a17fde",
    "sha256": "",
    "status": "qualified",
    "datetime": "",
    "proposer": "",
    "comment": ""
  },
  {
    "id": "262",
    "title": "Comatose state [Spinal Reflex]",
    "artist": "Spire / obj.7zs",
    "level": "4",
    "md5": "2bdc2d74aee220082ddd28e7524e26cc",
    "sha256": "",
    "status": "qualified",
    "datetime": "",
    "proposer": "",
    "comment": ""
  },
  {
    "id": "313",
    "title": "Hyper Fiber World Spectrum [Exotic Ethnic]",
    "artist": "Crimsona obj.7zs",
    "level": "4",
    "md5": "a539d62a700fe779dc528a99d320dad2",
    "sha256": "",
    "status": "qualified",
    "datetime": "",
    "proposer": "",
    "comment": ""
  },
  {
    "id": "140",
    "title": "Absolute Gate [四次元への扉]",
    "artist": "E0ri4 BGA:GAMEBAKA",
    "level": "5",
    "md5": "26eadbbfc2993a22e7372b5e9d42ef2e",
    "sha256": "",
    "status": "qualified",
    "datetime": "",
    "proposer": "",
    "comment": ""
  },
  {
    "id": "141",
    "title": "Air -GOD †-",
    "artist": "SHIKI / selene.",
    "level": "5",
    "md5": "4dacf54b5871fd7e367cfe5a067e5851",
    "sha256": "",
    "status": "qualified",
    "datetime": "",
    "proposer": "",
    "comment": ""
  },
  {
    "id": "142",
    "title": "Armageddon -Genocide-",
    "artist": "ZUN remixed by LeaF Movie:Optie/Illust:セシル◇タイト/selene.",
    "level": "5",
    "md5": "8122a17d61cf9a6f6a09c79238310465",
    "sha256": "",
    "status": "qualified",
    "datetime": "",
    "proposer": "",
    "comment": ""
  },
  {
    "id": "143",
    "title": "Aurora [64.96°N, 19.02°W]",
    "artist": "Lime / И",
    "level": "5",
    "md5": "59870e6c1b936fe10f8a8ed36f75b6be",
    "sha256": "",
    "status": "qualified",
    "datetime": "",
    "proposer": "",
    "comment": ""
  },
  {
    "id": "144",
    "title": "Be More Sadistic! (BMS Edit) -Genocide-",
    "artist": "黒木鳴海 Illust:アカツキユウ / selene.",
    "level": "5",
    "md5": "70cb09f3c2b58e8e49e28d481aa9435c",
    "sha256": "",
    "status": "qualified",
    "datetime": "",
    "proposer": "",
    "comment": ""
  },
  {
    "id": "145",
    "title": "Bumblebee(Hardtek_Refix) [Bombus]",
    "artist": "Neun_jack obj:Bombus",
    "level": "5",
    "md5": "8ab9993e183e8dd178d81fb7bf3183a5",
    "sha256": "",
    "status": "qualified",
    "datetime": "",
    "proposer": "",
    "comment": ""
  },
  {
    "id": "146",
    "title": "Critical Cannonball [Other]",
    "artist": "SEPHID obj:Omino",
    "level": "5",
    "md5": "d090cacfa84516b0cc8d4988c98e7a52",
    "sha256": "",
    "status": "qualified",
    "datetime": "",
    "proposer": "",
    "comment": ""
  },
  {
    "id": "147",
    "title": "Crush Alcohol [dumpass]",
    "artist": "shadow_bling obj. tyrcs",
    "level": "5",
    "md5": "ecb2d3f70570c3a3b45941ecc72c6b04",
    "sha256": "",
    "status": "qualified",
    "datetime": "",
    "proposer": "",
    "comment": ""
  },
  {
    "id": "148",
    "title": "Crystal Wind [IR]",
    "artist": "maxXx65535 obj:LuvTek",
    "level": "5",
    "md5": "899fde655fdd0213ab7df89fa577dfe8",
    "sha256": "",
    "status": "accepted",
    "datetime": "",
    "proposer": "",
    "comment": "POTY2021"
  },
  {
    "id": "149",
    "title": "Deublithick [INFELNO]",
    "artist": "激辛マニア /差分赤い人",
    "level": "5",
    "md5": "049accd5306faaa7c668fab8b17e10e1",
    "sha256": "",
    "status": "qualified",
    "datetime": "",
    "proposer": "",
    "comment": ""
  },
  {
    "id": "150",
    "title": "ELIMINATOR [A0]",
    "artist": "Cosmograph / yusi. / И",
    "level": "5",
    "md5": "f2106aa9aa8ccc0f96ab64c883c6b79e",
    "sha256": "",
    "status": "accepted",
    "datetime": "",
    "proposer": "",
    "comment": "POTY2021"
  },
  {
    "id": "151",
    "title": "endemize [triumph]",
    "artist": "あとぅす feat.つゆり花鈴 BGI:りーふぱいザウルス / obj:BAECON",
    "level": "5",
    "md5": "02a3f3b4707f863469ac7c67e12e9365",
    "sha256": "",
    "status": "accepted",
    "datetime": "",
    "proposer": "",
    "comment": "POTY2022"
  },
  {
    "id": "152",
    "title": "EVERLASTING HAPPiNESS↑ [AETERNUM]",
    "artist": "psi obj:mute",
    "level": "5",
    "md5": "498a9623f48f6dc5a7fef4e21adfa80a",
    "sha256": "",
    "status": "qualified",
    "datetime": "",
    "proposer": "",
    "comment": ""
  },
  {
    "id": "153",
    "title": "F13 [やばい]",
    "artist": "Judah BGA:Lucifer",
    "level": "5",
    "md5": "6c67f670599fdffb161eb2e1d798ffde",
    "sha256": "",
    "status": "qualified",
    "datetime": "",
    "proposer": "",
    "comment": ""
  },
  {
    "id": "154",
    "title": "FREEDOM DiVE - SINGULARITY",
    "artist": "xi obj: Alf vs BAECON",
    "level": "5",
    "md5": "a79a7531325f46f91960a43648296683",
    "sha256": "",
    "status": "qualified",
    "datetime": "",
    "proposer": "",
    "comment": ""
  },
  {
    "id": "155",
    "title": "FUELBLOODS -GOD-",
    "artist": "callasoiled / obj. marie",
    "level": "5",
    "md5": "be7fac015e47e921a2cb02623bc1ec41",
    "sha256": "",
    "status": "qualified",
    "datetime": "",
    "proposer": "",
    "comment": ""
  },
  {
    "id": "156",
    "title": "Gar♪goyle [コンプラ]",
    "artist": "Micelle / obj: Mary_Sue",
    "level": "5",
    "md5": "2ad657bdf59a0147b6f415a39b92f5b5",
    "sha256": "",
    "status": "accepted",
    "datetime": "",
    "proposer": "",
    "comment": "POTY2022"
  },
  {
    "id": "157",
    "title": "Happico Happico -Genocide-",
    "artist": "Music:しらいし / selene.",
    "level": "5",
    "md5": "7d80402a4a54bd90f14d46bb52677142",
    "sha256": "",
    "status": "qualified",
    "datetime": "",
    "proposer": "",
    "comment": ""
  },
  {
    "id": "158",
    "title": "Happy☆mooN (MAXIMUM)",
    "artist": "daiji+lobsak",
    "level": "5",
    "md5": "9ccadc27d033c4678ddb3e56289afc37",
    "sha256": "",
    "status": "qualified",
    "datetime": "",
    "proposer": "",
    "comment": ""
  },
  {
    "id": "159",
    "title": "Lewisia -EX-",
    "artist": "daiki / BGA:chromato graphy / obj : porter9876",
    "level": "5",
    "md5": "b0762b9db7de06bc0676ce7ff1b60270",
    "sha256": "",
    "status": "qualified",
    "datetime": "",
    "proposer": "",
    "comment": ""
  },
  {
    "id": "160",
    "title": "melody_express [絶叫]",
    "artist": "cromo /差分　赤い人 BGA: カントクP",
    "level": "5",
    "md5": "d03c69a9d8e7d785ed2884370b3ba26f",
    "sha256": "",
    "status": "qualified",
    "datetime": "",
    "proposer": "",
    "comment": ""
  },
  {
    "id": "161",
    "title": "MESMERA [SP ANOTHER]",
    "artist": "qfeileadh + 空読無 白眼",
    "level": "5",
    "md5": "96a5b7861d91d03cb82495abef5b8c8b",
    "sha256": "",
    "status": "accepted",
    "datetime": "",
    "proposer": "",
    "comment": "POTY2022"
  },
  {
    "id": "162",
    "title": "Psalms ～魂の還るばしょ～ [NIRVANA]",
    "artist": "qfeileadh＆レゾナンスもえこ mov:Maeus",
    "level": "5",
    "md5": "b0279420063b1f5bc8f16c36cf990f0f",
    "sha256": "",
    "status": "accepted",
    "datetime": "",
    "proposer": "",
    "comment": "POTY2020"
  },
  {
    "id": "163",
    "title": "puppies [Pentagon]",
    "artist": "tdef",
    "level": "5",
    "md5": "d8355db1f45727bcd468242ba751c307",
    "sha256": "",
    "status": "qualified",
    "datetime": "",
    "proposer": "",
    "comment": ""
  },
  {
    "id": "164",
    "title": "Rabbits [Maryther]",
    "artist": "Est / BGA:Johnny / OBJ:Mary_Sue",
    "level": "5",
    "md5": "ecafeddfc8731c5243ce3c5165767715",
    "sha256": "",
    "status": "qualified",
    "datetime": "",
    "proposer": "",
    "comment": ""
  },
  {
    "id": "165",
    "title": "Retronika [RETROACTIVE]",
    "artist": "38k obj:qfeileadh",
    "level": "5",
    "md5": "ac1104e67869c22f1049096ee6ac3c87",
    "sha256": "",
    "status": "accepted",
    "datetime": "",
    "proposer": "",
    "comment": "POTY2022"
  },
  {
    "id": "166",
    "title": "Revenant [Vanquishment]",
    "artist": "Juggernaut. bga:drowseland obj:Rian",
    "level": "5",
    "md5": "3b693c15dbdf39f31b6d94477f091900",
    "sha256": "",
    "status": "qualified",
    "datetime": "",
    "proposer": "",
    "comment": ""
  },
  {
    "id": "168",
    "title": "Sunset Toybox [EXTRA]",
    "artist": "テヅカ x Aoi feat.桃雛なの / obj:夢瑠",
    "level": "5",
    "md5": "b68e4ddc153ab9b9391f3d9a2f856e7a",
    "sha256": "",
    "status": "accepted",
    "datetime": "",
    "proposer": "",
    "comment": "POTY2021"
  },
  {
    "id": "169",
    "title": "That's the style!! [Hexagon]",
    "artist": "nez obj.hex",
    "level": "5",
    "md5": "7867d3bf5cc5af9289f33313eaceb2ed",
    "sha256": "",
    "status": "qualified",
    "datetime": "",
    "proposer": "",
    "comment": ""
  },
  {
    "id": "170",
    "title": "Theine [GOD]",
    "artist": "crossworld / obj:Lian",
    "level": "5",
    "md5": "e5d9c4094ab7c6790e655ed95550a6ba",
    "sha256": "",
    "status": "qualified",
    "datetime": "",
    "proposer": "",
    "comment": ""
  },
  {
    "id": "172",
    "title": "Ultimate Dream [INSANE]",
    "artist": "Star* + Cryo-Myosotis",
    "level": "5",
    "md5": "1e363649c9762aa94c4b7f4a6eb92302",
    "sha256": "",
    "status": "qualified",
    "datetime": "",
    "proposer": "",
    "comment": ""
  },
  {
    "id": "173",
    "title": "Unlucky Tornado [Insane]",
    "artist": "Setca. / obj:C4",
    "level": "5",
    "md5": "a3d0fe26e62806a85e47b543b42c1dfd",
    "sha256": "",
    "status": "qualified",
    "datetime": "",
    "proposer": "",
    "comment": ""
  },
  {
    "id": "174",
    "title": "アイーシャの剣 -Forcing breakthrough- [終点]",
    "artist": "Alicia* / obj.ぶんぺ～",
    "level": "5",
    "md5": "2c6b81335186788266c3633582240c98",
    "sha256": "",
    "status": "qualified",
    "datetime": "",
    "proposer": "",
    "comment": ""
  },
  {
    "id": "175",
    "title": "タマモッチ",
    "artist": "LisicA movie : ルゼ(LuzeriA) / illust : Orphee / pattern for some reason",
    "level": "5",
    "md5": "773c00048c49a0847bca38eba748fba9",
    "sha256": "",
    "status": "accepted",
    "datetime": "",
    "proposer": "",
    "comment": "POTY2021"
  },
  {
    "id": "176",
    "title": "ロッカー -Ex+-",
    "artist": "ATEMAK/さ/otoshi.b",
    "level": "5",
    "md5": "1a477f8c6c7ae8ac41ff44d24afc4e10",
    "sha256": "",
    "status": "qualified",
    "datetime": "",
    "proposer": "",
    "comment": ""
  },
  {
    "id": "178",
    "title": "白の魔法の光 [INFERNO]",
    "artist": "こどものなみだ /差分 赤い人",
    "level": "5",
    "md5": "e08c45e9f6e4af3851455201bee6e202",
    "sha256": "",
    "status": "qualified",
    "datetime": "",
    "proposer": "",
    "comment": ""
  },
  {
    "id": "258",
    "title": "JULIAN \"for B.O.F. 2009\"",
    "artist": "Queen P.A.L. VJ KINTA / obj.7zs",
    "level": "5",
    "md5": "1e9c2d49a28494f5db6541e3bf1c2eae",
    "sha256": "",
    "status": "qualified",
    "datetime": "",
    "proposer": "",
    "comment": ""
  },
  {
    "id": "297",
    "title": "Qualia [情け無用]",
    "artist": "Junk / 鬼コーチ : 発汗BMS",
    "level": "5",
    "md5": "7c357326e3473309b0f17b3715ebf149",
    "sha256": "",
    "status": "qualified",
    "datetime": "",
    "proposer": "",
    "comment": ""
  },
  {
    "id": "348",
    "title": "BiBiRi [Fatal-Foudre]",
    "artist": "STASTA BGA : nanairo obj.7zs",
    "level": "5",
    "md5": "e3363aedcc840b104e33efa25d96f108",
    "sha256": "",
    "status": "qualified",
    "datetime": "",
    "proposer": "",
    "comment": ""
  },
  {
    "id": "367",
    "title": "Play Me Your Love Song [Hexagon]",
    "artist": "Kyuzo Sameura feat. a-m obj.hex",
    "level": "5",
    "md5": "ffb9dfbb5f7fd65746eeffe6b31fa66d",
    "sha256": "",
    "status": "qualified",
    "datetime": "",
    "proposer": "",
    "comment": ""
  },
  {
    "id": "395",
    "title": "Falling in LOVE [You're special to me...]",
    "artist": "SOMON obj:EGRET.",
    "level": "5",
    "md5": "66e996d348123b13b231b2b01847e3f8",
    "sha256": "",
    "status": "qualified",
    "datetime": "",
    "proposer": "",
    "comment": ""
  },
  {
    "id": "443",
    "title": "トゥンカロン・ティータイム [Monogon]",
    "artist": "kasとFaine obj:1008",
    "level": "5",
    "md5": "ce913fbb15a985c11a2b1e7b4605d6a9",
    "sha256": "",
    "status": "qualified",
    "datetime": "",
    "proposer": "",
    "comment": ""
  },
  {
    "id": "793",
    "title": "Prayer [LAST BOSS]",
    "artist": "Kankitsu obj:BAECON",
    "level": "5",
    "md5": "81d2bc2d271c2bc318f478a59cdfb507",
    "sha256": "",
    "status": "qualified",
    "datetime": "",
    "proposer": "",
    "comment": ""
  },
  {
    "id": "96",
    "title": "★So SweeT LittlE HearT★ (GOD)",
    "artist": "kbwnk max / obj:uet",
    "level": "6",
    "md5": "365816fd4a3bc8df11fe10823de3fd2e",
    "sha256": "",
    "status": "qualified",
    "datetime": "",
    "proposer": "",
    "comment": ""
  },
  {
    "id": "177",
    "title": "日溜りの街－あ！－ [ラブジャスGOD絶対倒す]",
    "artist": "猫蟹丸 / obj:onmaco",
    "level": "6",
    "md5": "97bccaa6b2bcf847735aff067e4b493b",
    "sha256": "",
    "status": "qualified",
    "datetime": "",
    "proposer": "",
    "comment": ""
  },
  {
    "id": "179",
    "title": "[line:theta] [HYPERLIMINAL]",
    "artist": "nitro / obj. marie",
    "level": "6",
    "md5": "0c743a2d771c22f1d7a45e40a299c454",
    "sha256": "",
    "status": "accepted",
    "datetime": "",
    "proposer": "",
    "comment": "POTY2022"
  },
  {
    "id": "180",
    "title": "Agilion [OVERJOY]",
    "artist": "LeaF",
    "level": "6",
    "md5": "01d9ea966de753dee21609a2b69a68e0",
    "sha256": "",
    "status": "accepted",
    "datetime": "",
    "proposer": "",
    "comment": "POTY2022"
  },
  {
    "id": "181",
    "title": "Black Lotus [Other]",
    "artist": "wa. / 百舌谷 obj:Omino",
    "level": "6",
    "md5": "204febd6a2f38c3d4f0f2e3278b6a960",
    "sha256": "",
    "status": "qualified",
    "datetime": "",
    "proposer": "",
    "comment": ""
  },
  {
    "id": "182",
    "title": "CODE-F -soar to the Frontier- [frontier]",
    "artist": "kei iwata/xenothium",
    "level": "6",
    "md5": "d7cae692a376eaeaa6355c8d2fa3d73b",
    "sha256": "",
    "status": "qualified",
    "datetime": "",
    "proposer": "",
    "comment": ""
  },
  {
    "id": "183",
    "title": "Cold Breath -Ragnarok-",
    "artist": "SHIKI / selene.",
    "level": "6",
    "md5": "8b8634ba54a3e177f0d174dfd0799843",
    "sha256": "",
    "status": "qualified",
    "datetime": "",
    "proposer": "",
    "comment": ""
  },
  {
    "id": "185",
    "title": "F13 [machete]",
    "artist": "Judah BGA:Lucifer obj : ランダマイザ",
    "level": "6",
    "md5": "fe553e311da117c117a3ee3591557a70",
    "sha256": "",
    "status": "qualified",
    "datetime": "",
    "proposer": "",
    "comment": ""
  },
  {
    "id": "186",
    "title": "Fluctuate [Hexagon]",
    "artist": "ALFOU obj.hex",
    "level": "6",
    "md5": "a78f66ec6dc23a9f9ad36b57cb7b3e5b",
    "sha256": "",
    "status": "accepted",
    "datetime": "",
    "proposer": "",
    "comment": "POTY2021"
  },
  {
    "id": "187",
    "title": "HEXPERUS [ZENITH]",
    "artist": "qfeileadh&のあ mov:Kengo Nakao",
    "level": "6",
    "md5": "46a2c6c0f73f1520feac4228982eb17d",
    "sha256": "",
    "status": "accepted",
    "datetime": "",
    "proposer": "",
    "comment": "POTY2021"
  },
  {
    "id": "188",
    "title": "Marmot [BUSTER]",
    "artist": "Lian",
    "level": "6",
    "md5": "280769115bfe876243b1b03706ee0081",
    "sha256": "",
    "status": "qualified",
    "datetime": "",
    "proposer": "",
    "comment": ""
  },
  {
    "id": "189",
    "title": "not 桜 (KOOKY)",
    "artist": "MITCH DOWNVELL / obj:qfeileadh",
    "level": "6",
    "md5": "0a2ef1a74e2bf188bc129066c95b6e86",
    "sha256": "",
    "status": "accepted",
    "datetime": "",
    "proposer": "",
    "comment": "POTY2020"
  },
  {
    "id": "190",
    "title": "NS22 [7key Another+]",
    "artist": "3034 obj:hoi2",
    "level": "6",
    "md5": "c20426480da2741a37d2fdf5f70eaf1b",
    "sha256": "",
    "status": "qualified",
    "datetime": "",
    "proposer": "",
    "comment": ""
  },
  {
    "id": "191",
    "title": "Number Y [Other]",
    "artist": "Lemi. obj:Omino",
    "level": "6",
    "md5": "30bffbc5f5a74d005bd38d395f798107",
    "sha256": "",
    "status": "qualified",
    "datetime": "",
    "proposer": "",
    "comment": ""
  },
  {
    "id": "192",
    "title": "overtrue [Other]",
    "artist": "Larimar Movie : Hauynite / obj : Omino",
    "level": "6",
    "md5": "9ac398d3e963c9338d3d0c8005bd097b",
    "sha256": "",
    "status": "accepted",
    "datetime": "",
    "proposer": "",
    "comment": "POTY2019"
  },
  {
    "id": "193",
    "title": "SYNTHETICS [Hexagon]",
    "artist": "Soba Yamamori obj.hex",
    "level": "6",
    "md5": "26790f4cd7ffda85c52b63e5ed24da4f",
    "sha256": "",
    "status": "accepted",
    "datetime": "",
    "proposer": "",
    "comment": "POTY2019"
  },
  {
    "id": "194",
    "title": "tinnitus -Madness-",
    "artist": "SP-# / obj : LindBlum",
    "level": "6",
    "md5": "d49874c9835571a8d892e6ed6a0dcaef",
    "sha256": "",
    "status": "qualified",
    "datetime": "",
    "proposer": "",
    "comment": ""
  },
  {
    "id": "195",
    "title": "イナリッチ [POOR]",
    "artist": "LisicA movie : 自動車原付 / illust : Orphee / obj:tyrcs",
    "level": "6",
    "md5": "23c01dd80a6220d250371992a1cf80cd",
    "sha256": "",
    "status": "accepted",
    "datetime": "",
    "proposer": "",
    "comment": "POTY2022"
  },
  {
    "id": "197",
    "title": "人形楽団 ～ Puppet Ensemble ・∀・ ～",
    "artist": "Yu^ta / obj:Omino",
    "level": "6",
    "md5": "c00b5965971e46fd9da5575160e5b9af",
    "sha256": "",
    "status": "qualified",
    "datetime": "",
    "proposer": "",
    "comment": ""
  },
  {
    "id": "341",
    "title": "先手必勝戦闘機　鳳 [Vent Divin]",
    "artist": "Dr.A (BGA:八嶋) obj.7zs",
    "level": "6",
    "md5": "dc10488184abbc35bbf234596cbea83f",
    "sha256": "",
    "status": "qualified",
    "datetime": "",
    "proposer": "",
    "comment": ""
  },
  {
    "id": "426",
    "title": "ワンダフォー・パラダイス [Wonderful]",
    "artist": "翡乃イスカ obj:BAECON",
    "level": "6",
    "md5": "a4abd9d8cdd2cbda31d949474e52219d",
    "sha256": "",
    "status": "qualified",
    "datetime": "",
    "proposer": "",
    "comment": ""
  },
  {
    "id": "548",
    "title": "リクロスフェイト [INSANE]",
    "artist": "あとぅす BGI:りーふぱいザウルス",
    "level": "6",
    "md5": "05e493cef2ff307aba146c8cb3be8ddd",
    "sha256": "",
    "status": "qualified",
    "datetime": "",
    "proposer": "",
    "comment": ""
  },
  {
    "id": "198",
    "title": "-雪月花- [Hexagon]",
    "artist": "SOMON obj.hex",
    "level": "7",
    "md5": "0c5a038e9fedb4c799051da04b3925d0",
    "sha256": "",
    "status": "accepted",
    "datetime": "",
    "proposer": "",
    "comment": "POTY2019"
  },
  {
    "id": "199",
    "title": "#DoomeyTunes [phi]",
    "artist": "Louie Fibonacci feat. ricono obj:qfeileadh",
    "level": "7",
    "md5": "7f2cbe01342d3935dd6e72a7ef2b4aa3",
    "sha256": "",
    "status": "accepted",
    "datetime": "",
    "proposer": "",
    "comment": "POTY2021"
  },
  {
    "id": "200",
    "title": "Breeze -SUMMER BOSS-",
    "artist": "Kankitsu",
    "level": "7",
    "md5": "bd97bff3356c5d85dd3490c15d25035b",
    "sha256": "",
    "status": "qualified",
    "datetime": "",
    "proposer": "",
    "comment": ""
  },
  {
    "id": "201",
    "title": "Chronomia -LAST BOSS-",
    "artist": "Lime / inukoro",
    "level": "7",
    "md5": "5b125766f8a8ccfbecf172ca03961d07",
    "sha256": "",
    "status": "qualified",
    "datetime": "",
    "proposer": "",
    "comment": ""
  },
  {
    "id": "202",
    "title": "Chronostasis [Reincarnation]",
    "artist": "黒皇帝 / obj:O Movie: 6XeNoN9",
    "level": "7",
    "md5": "a06c88e7421b463a9d2d8b0e606eea97",
    "sha256": "",
    "status": "accepted",
    "datetime": "",
    "proposer": "",
    "comment": "POTY2021"
  },
  {
    "id": "203",
    "title": "Epatoivo LdsRmx [BlackAnother]",
    "artist": "Le Dos-on",
    "level": "7",
    "md5": "4734dfe0cc9a169269dda03c6f8f11e5",
    "sha256": "",
    "status": "qualified",
    "datetime": "",
    "proposer": "",
    "comment": ""
  },
  {
    "id": "204",
    "title": "EVERLASTING HAPPiNESS↑ [UNHAPPY]",
    "artist": "psi obj:O",
    "level": "7",
    "md5": "5527d3a3fac524025a32727a6499e14b",
    "sha256": "",
    "status": "qualified",
    "datetime": "",
    "proposer": "",
    "comment": ""
  },
  {
    "id": "205",
    "title": "Finixe -LEGENDA EST A MYTH-",
    "artist": "Silentroom × iimo obj : BAECON",
    "level": "7",
    "md5": "54d4facf3ab605c7b5c61177a75ae223",
    "sha256": "",
    "status": "qualified",
    "datetime": "",
    "proposer": "",
    "comment": ""
  },
  {
    "id": "207",
    "title": "NS18 [Plus]",
    "artist": "3034 / O Anomie / IllusionRain",
    "level": "7",
    "md5": "0c44de22eaf1ac81895773e217f48ee8",
    "sha256": "",
    "status": "qualified",
    "datetime": "",
    "proposer": "",
    "comment": ""
  },
  {
    "id": "208",
    "title": "PUPA -Destiny-",
    "artist": "モリモリあつし / obj : LindBlum",
    "level": "7",
    "md5": "20a354a7af4e6ce78ce0309024334d16",
    "sha256": "",
    "status": "qualified",
    "datetime": "",
    "proposer": "",
    "comment": ""
  },
  {
    "id": "209",
    "title": "Shiny☆Strike!!! [Beyond the Future]",
    "artist": "otoshi.b × みゅい × はしたかさん × BAECON",
    "level": "7",
    "md5": "45681e84e18abc0b7056db209a694309",
    "sha256": "",
    "status": "accepted",
    "datetime": "",
    "proposer": "",
    "comment": "POTY2020"
  },
  {
    "id": "210",
    "title": "sweet pop [saccharine]",
    "artist": "Ym1024 feat. lamie* Illustration : 恋々 Obj : И",
    "level": "7",
    "md5": "5497cd98fc1a770a553ebe1068f8c1e9",
    "sha256": "",
    "status": "qualified",
    "datetime": "",
    "proposer": "",
    "comment": ""
  },
  {
    "id": "211",
    "title": "Valkyrie Revolutia [Super Hexagon]",
    "artist": "Sakamiya obj.hex",
    "level": "7",
    "md5": "5267eb8a7dde7bced341bd0e261d4008",
    "sha256": "",
    "status": "qualified",
    "datetime": "",
    "proposer": "",
    "comment": ""
  },
  {
    "id": "212",
    "title": "スナレ",
    "artist": "Zris feat. Green obj. tyrcs",
    "level": "7",
    "md5": "82aeb140cc56a5618c14cffc97c60d47",
    "sha256": "",
    "status": "accepted",
    "datetime": "",
    "proposer": "",
    "comment": "POTY2022"
  },
  {
    "id": "213",
    "title": "テウメッサ",
    "artist": "LisicA movie : ルゼ(LuzeriA) / illust : Orphee / pattern for some reason +.5",
    "level": "7",
    "md5": "40158096b8842e0c44f99a77951f032f",
    "sha256": "",
    "status": "accepted",
    "datetime": "",
    "proposer": "",
    "comment": "POTY2020"
  },
  {
    "id": "216",
    "title": "薄雲 [六角形的+]",
    "artist": "薄荷堂 龍 obj.hex / reobj.hoax",
    "level": "7",
    "md5": "51d1efb20773d137cbb5b7e7aef8d933",
    "sha256": "",
    "status": "accepted",
    "datetime": "",
    "proposer": "",
    "comment": "POTY2022"
  },
  {
    "id": "217",
    "title": "臨終 [Sufrimiento]",
    "artist": "Lunatic Sounds BGA : Smin / obj : MirariMaker",
    "level": "7",
    "md5": "04545fb5492a545c32f47691f7a98da7",
    "sha256": "",
    "status": "qualified",
    "datetime": "",
    "proposer": "",
    "comment": ""
  },
  {
    "id": "259",
    "title": "LOSTSILVER [Perish Song]",
    "artist": "DJ Ash Ketchum / obj.7zs",
    "level": "7",
    "md5": "2720eea7d90686a3be9ac606758f2763",
    "sha256": "",
    "status": "qualified",
    "datetime": "",
    "proposer": "",
    "comment": ""
  },
  {
    "id": "384",
    "title": "玉響サーチライト -Shiny☆Strike!!!-",
    "artist": "otoshi.b × みゅい & tolz × はしたかさん & 七海",
    "level": "7",
    "md5": "310f70c1f1b3be8437844a960027b880",
    "sha256": "",
    "status": "qualified",
    "datetime": "",
    "proposer": "",
    "comment": ""
  },
  {
    "id": "425",
    "title": "SHI☆A☆WA☆SE [MASTER]",
    "artist": "eye burn Reading: 冬乃桜 / obj.Mallow♪",
    "level": "7",
    "md5": "a43af3297f4f1e418042b1e72a44f248",
    "sha256": "",
    "status": "qualified",
    "datetime": "",
    "proposer": "",
    "comment": ""
  },
  {
    "id": "218",
    "title": "Ascension to Heaven [Firmament]",
    "artist": "xi obj:otoshi.b",
    "level": "8",
    "md5": "4dc33afda02f2e2e31835e5b099c494e",
    "sha256": "",
    "status": "qualified",
    "datetime": "",
    "proposer": "",
    "comment": ""
  },
  {
    "id": "219",
    "title": "Blue Delaygoon [フルマラソン]",
    "artist": "kanone ランナー : あんた",
    "level": "8",
    "md5": "cbc9a270b836804d61294eb7519d3d90",
    "sha256": "",
    "status": "accepted",
    "datetime": "",
    "proposer": "",
    "comment": "POTY2020"
  },
  {
    "id": "220",
    "title": "F13 [Conclusion]",
    "artist": "Judah BGA:Lucifer obj:VINYL",
    "level": "8",
    "md5": "f1609dbcfe0ff7f4eacc7d8ac5e960b5",
    "sha256": "",
    "status": "qualified",
    "datetime": "",
    "proposer": "",
    "comment": ""
  },
  {
    "id": "221",
    "title": "G-Bass / mild_hihat.wav REAL LIFE",
    "artist": "Theme -----",
    "level": "8",
    "md5": "7fc3fee2272490597e2ac819ecad4a67",
    "sha256": "",
    "status": "accepted",
    "datetime": "",
    "proposer": "",
    "comment": "POTY2022"
  },
  {
    "id": "222",
    "title": "Life is PIANO [Other]",
    "artist": "Junk obj:Omino",
    "level": "8",
    "md5": "fdb9d7d8eaca594231dda88b539253cb",
    "sha256": "",
    "status": "accepted",
    "datetime": "",
    "proposer": "",
    "comment": "POTY2019"
  },
  {
    "id": "223",
    "title": "Stellaria [LAST VOYAGE]",
    "artist": "Lime obj:NoName",
    "level": "8",
    "md5": "8b56f71a2c636e7bf94191e874f1f854",
    "sha256": "",
    "status": "accepted",
    "datetime": "",
    "proposer": "",
    "comment": "POTY2020"
  },
  {
    "id": "224",
    "title": "the lost dedicated [life]",
    "artist": "哀愁マニア",
    "level": "8",
    "md5": "8f2a82e4f1f3e299c5d761a4c673b9ae",
    "sha256": "",
    "status": "qualified",
    "datetime": "",
    "proposer": "",
    "comment": ""
  },
  {
    "id": "225",
    "title": "tinnitus [Other]",
    "artist": "SP-# obj:Omino",
    "level": "8",
    "md5": "655052be72cdca0efda4c89041c056e3",
    "sha256": "",
    "status": "qualified",
    "datetime": "",
    "proposer": "",
    "comment": ""
  },
  {
    "id": "226",
    "title": "ドキッ！けふぃーとひ・み・つｖのサッカータイム☆☆ニャホニャホしても、いいんですよ･･･？　 ～KEFIFAワールドカップ編 We love 汚滝健太郎～",
    "artist": "11.Soccer Team",
    "level": "8",
    "md5": "d0e8c3ea6fec34783b1e01ed661f4b28",
    "sha256": "",
    "status": "qualified",
    "datetime": "",
    "proposer": "",
    "comment": ""
  },
  {
    "id": "227",
    "title": "天空の城ヴェリエル [EX]",
    "artist": "うえつ氏 /さ",
    "level": "8",
    "md5": "efc800022aa4b92e1fdb934e829094d8",
    "sha256": "",
    "status": "qualified",
    "datetime": "",
    "proposer": "",
    "comment": ""
  },
  {
    "id": "229",
    "title": "Lolita Scaffold [FATALITY]",
    "artist": "Iron Maiden Strength / obj:O BGA / Seagle Asakura",
    "level": "9",
    "md5": "a548a8658498fe3d51ba66ae0c8a9340",
    "sha256": "",
    "status": "qualified",
    "datetime": "",
    "proposer": "",
    "comment": ""
  },
  {
    "id": "230",
    "title": "Terpsichore [Other]",
    "artist": "Jun Kuroda obj:Omino",
    "level": "9",
    "md5": "f5ab931263d62a063b1bce32bfae492d",
    "sha256": "",
    "status": "accepted",
    "datetime": "",
    "proposer": "",
    "comment": "POTY2019"
  },
  {
    "id": "232",
    "title": "Armageddon [Other]",
    "artist": "ZUN remixed by LeaF Movie:Optie/Illust:セシル◇タイト/Obj:Omino",
    "level": "10",
    "md5": "f6f6de31a6a7501e329374fc17b878dc",
    "sha256": "",
    "status": "accepted",
    "datetime": "",
    "proposer": "",
    "comment": "POTY2020"
  },
  {
    "id": "233",
    "title": "F13",
    "artist": "Judah / obj:Monsta BGA:Lucifer",
    "level": "10",
    "md5": "3863e522e108b059d816443fb7b3fc5f",
    "sha256": "",
    "status": "qualified",
    "datetime": "",
    "proposer": "",
    "comment": ""
  },
  {
    "id": "234",
    "title": "Nyan-Nyan Naughty Night [N,N,N′,N′-Tetramethylethylenediamine－]",
    "artist": "かたぎり / おたく BGI: morph",
    "level": "10",
    "md5": "57073fac4f6b8f6f298f1caf82effdb0",
    "sha256": "",
    "status": "qualified",
    "datetime": "",
    "proposer": "",
    "comment": ""
  },
  {
    "id": "235",
    "title": "マッドメチャクチャニズム",
    "artist": "69 de 74 BGI:れおん / obj.hex",
    "level": "10",
    "md5": "2c72cf3fcc47e7cbc82c3f9075da64a4",
    "sha256": "",
    "status": "qualified",
    "datetime": "",
    "proposer": "",
    "comment": ""
  },
  {
    "id": "236",
    "title": "マッドメチャクチャニズム [Hexagon]",
    "artist": "69 de 74 BGI:れおん / obj.hex",
    "level": "10",
    "md5": "2f6e2c4f802c932f00b3b8ee4c593083",
    "sha256": "",
    "status": "qualified",
    "datetime": "",
    "proposer": "",
    "comment": ""
  },
  {
    "id": "237",
    "title": "Boxel Adventure [Null]",
    "artist": "7mai / obj: ∇・tachyon",
    "level": "11",
    "md5": "241e82b318e97de873efaa8d9f107755",
    "sha256": "",
    "status": "accepted",
    "datetime": "",
    "proposer": "",
    "comment": "POTY2021"
  },
  {
    "id": "238",
    "title": "Celestial Axes [Other]",
    "artist": "nmk / わっふゑ obj:Omino",
    "level": "11",
    "md5": "22f71b0463955fcedb84eca9d09e60ca",
    "sha256": "",
    "status": "qualified",
    "datetime": "",
    "proposer": "",
    "comment": ""
  },
  {
    "id": "239",
    "title": "日溜りの街－あ！－ (BMS MASTER)",
    "artist": "猫蟹丸 / obj: black train",
    "level": "11",
    "md5": "5c02488ed7f347cf9b78398fa8982e69",
    "sha256": "",
    "status": "qualified",
    "datetime": "",
    "proposer": "",
    "comment": ""
  },
  {
    "id": "240",
    "title": "bEyOnD",
    "artist": "Lime / Crude Sound Adder",
    "level": "12",
    "md5": "cdf5b366fc7e518bcb9ea1e9a169e5ea",
    "sha256": "",
    "status": "qualified",
    "datetime": "",
    "proposer": "",
    "comment": ""
  },
  {
    "id": "241",
    "title": "Nyan-Nyan Naughty Night [N,N,N′,N′-Tetramethylethylenediamine]",
    "artist": "かたぎり / おたく BGI: morph",
    "level": "12",
    "md5": "e01344b7d64159e7aa28b29d32ea6351",
    "sha256": "",
    "status": "accepted",
    "datetime": "",
    "proposer": "",
    "comment": "POTY2021"
  },
  {
    "id": "242",
    "title": "the lost dedicated [life normal]",
    "artist": "哀愁マニア",
    "level": "12",
    "md5": "fed59d3b700499c9207c4995d160cc9a",
    "sha256": "",
    "status": "accepted",
    "datetime": "",
    "proposer": "",
    "comment": "POTY2022"
  },
  {
    "id": "4",
    "title": "FREEDOM DiVE [FOUR DIMENSIONS]",
    "artist": "xi / air",
    "level": "FDFD",
    "md5": "c46a81cb184f5a804c119930d6eba748",
    "sha256": "",
    "status": "accepted",
    "datetime": "",
    "proposer": "",
    "comment": ""
  },
  {
    "id": "7",
    "title": "FREEDOM DiVE [FOUR DIMENSIONS:PRO]",
    "artist": "xi / air / Ds",
    "level": "FDFD",
    "md5": "0fec4ef0a473d0a888f63be79a90b001",
    "sha256": "",
    "status": "accepted",
    "datetime": "",
    "proposer": "",
    "comment": ""
  },
  {
    "id": "8",
    "title": "FREEDOM DiVE [FOUR DIMENSIONS:TRIAL]",
    "artist": "xi / air / VINYL",
    "level": "FDFD",
    "md5": "c46d7c72702c98c4120b7079e8b3a246",
    "sha256": "",
    "status": "accepted",
    "datetime": "",
    "proposer": "",
    "comment": ""
  },
  {
    "id": "3",
    "title": "Love & Justice [GOD]",
    "artist": "フロン / ラズベリル / obj: black train",
    "level": "ラブゴ",
    "md5": "39d0732ef7fee9ad0c8b044ccbe8a396",
    "sha256": "",
    "status": "accepted",
    "datetime": "",
    "proposer": "",
    "comment": ""
  },
  {
    "id": "5",
    "title": "Love & Justice [Hand Crusher]",
    "artist": "フロン / ラズベリル / obj : lemon_aided",
    "level": "ラブゴ",
    "md5": "819a5580904dc0146995b52f12619517",
    "sha256": "",
    "status": "accepted",
    "datetime": "",
    "proposer": "",
    "comment": ""
  },
  {
    "id": "6",
    "title": "Love & Justice [ぷにあな7]",
    "artist": "フロン / ラズベリル obj:ちいかわ",
    "level": "ラブゴ",
    "md5": "57609cc0ebb67eebed15ffc8e2b82ab2",
    "sha256": "",
    "status": "accepted",
    "datetime": "",
    "proposer": "",
    "comment": ""
  },
  {
    "id": "1",
    "title": "Magical Love Words [マジカル横認識]",
    "artist": "源屋feat.ユスラ obj:trainer",
    "level": "体育祭",
    "md5": "e18550050e4ee6008798111d4a63e81a",
    "sha256": "",
    "status": "accepted",
    "datetime": "",
    "proposer": "",
    "comment": ""
  },
  {
    "id": "2",
    "title": "Magical Love Words [フィジカル横認識]",
    "artist": "源屋feat.ユスラ obj:trainer",
    "level": "体育祭",
    "md5": "407c8e043a446c9dc99fc1ca97eb2fb5",
    "sha256": "",
    "status": "accepted",
    "datetime": "",
    "proposer": "",
    "comment": ""
  }
]