{
  "name": "K-SPIN発狂難易度表",
  "symbol": "KS",
  "url": "https://rawgit.com/rib2bit/BMS-database/master/tables/K-SPIN%E7%99%BA%E7%8B%82%E9%9B%A3%E6%98%93%E5%BA%A6%E8%A1%A8/table.html",
  "comment": "Mirror by Ribbit",
  "date": "",
  "state": "",
  "tag1": "SP",
  "tag2": "Self-made Chart Only",
  "tag_order": "1",
  "url_data_json": "https://rawgit.com/rib2bit/BMS-database/master/tables/K-SPIN%E7%99%BA%E7%8B%82%E9%9B%A3%E6%98%93%E5%BA%A6%E8%A1%A8/data.json",
  "url_header_json": "https://rawgit.com/rib2bit/BMS-database/master/tables/K-SPIN%E7%99%BA%E7%8B%82%E9%9B%A3%E6%98%93%E5%BA%A6%E8%A1%A8/header.json"
}